CTDFjorder/CTDFjorder.py
CTDFjorder/__init__.py
CTDFjorder_git-0.0.15.dist-info/METADATA
CTDFjorder_git-0.0.15.dist-info/WHEEL
CTDFjorder_git-0.0.15.dist-info/entry_points.txt
CTDFjorder_git-0.0.15.dist-info/top_level.txt
CTDFjorder_git-0.0.15.dist-info/RECORD
