Metadata-Version: 2.1
Name: CTDFjorder-git
Version: 0.0.15
Summary: A package for processing and analyzing CTD data.
Home-page: https://github.com/nikothomas/CTDFjorder
Author: Nikolas Yanek-Chrones
Author-email: nikojb1001@gmail.com
Project-URL: Homepage, https://github.com/nikothomas/CTDFjorder
Project-URL: Issues, https://github.com/nikothomas/CTDFjorder/issues
Keywords: CTD
Classifier: Development Status :: 3 - Alpha
Classifier: Programming Language :: Python :: 3
Classifier: License :: OSI Approved :: MIT License
Classifier: Operating System :: OS Independent
Requires-Python: >=3.11
Requires-Dist: numpy >=1.26.4
Requires-Dist: pandas >=2.2.1
Requires-Dist: gsw >=3.6.17
Requires-Dist: matplotlib >=3.8.4
Requires-Dist: statsmodels >=0.14.0
Requires-Dist: tabulate >=0.9.0
Requires-Dist: pyrsktools ==0.1.9
Requires-Dist: openpyxl >=3.1.2
Requires-Dist: setuptools
